limitless/__init__.py
limitless/cli.py
limitless/extractor.py
limitless/model.py
limitless/simulator.py
limitless/train.py
limitless/templates/debug/template.css
limitless/templates/debug/template.html
limitless/templates/debug/template.js
limitless/templates/ds4/base-black.svg
limitless/templates/ds4/base-blue.svg
limitless/templates/ds4/base-red.svg
limitless/templates/ds4/base-white.svg
limitless/templates/ds4/bumper.svg
limitless/templates/ds4/buttons.svg
limitless/templates/ds4/config.json
limitless/templates/ds4/disconnected.svg
limitless/templates/ds4/dpad.svg
limitless/templates/ds4/meta.svg
limitless/templates/ds4/start.svg
limitless/templates/ds4/sticks.svg
limitless/templates/ds4/template.css
limitless/templates/ds4/template.html
limitless/templates/ds4/template.js
limitless/templates/ds4/touchpad.svg
limitless/templates/ds4/triggers.svg
limitless/templates/xbox-one/base-black.svg
limitless/templates/xbox-one/base-white.svg
limitless/templates/xbox-one/bumper.svg
limitless/templates/xbox-one/buttons.svg
limitless/templates/xbox-one/config.json
limitless/templates/xbox-one/disconnected.svg
limitless/templates/xbox-one/dpad.svg
limitless/templates/xbox-one/start-select.svg
limitless/templates/xbox-one/stick.svg
limitless/templates/xbox-one/template.css
limitless/templates/xbox-one/template.html
limitless/templates/xbox-one/template.js
limitless/templates/xbox-one/trigger.svg
limitless_ai-0.1.0.dist-info/METADATA
limitless_ai-0.1.0.dist-info/WHEEL
limitless_ai-0.1.0.dist-info/entry_points.txt
limitless_ai-0.1.0.dist-info/top_level.txt
limitless_ai-0.1.0.dist-info/RECORD
