Metadata-Version: 2.4
Name: limitless-ai
Version: 0.1.0
Summary: Universal AI Game Agent
Author: Haum Lab
License: MIT
Requires-Python: >=3.10
Requires-Dist: opencv-python
Requires-Dist: numpy
Requires-Dist: pandas
Requires-Dist: cairosvg
Requires-Dist: torch
Requires-Dist: torchvision
Requires-Dist: tqdm
Requires-Dist: scikit-learn
Requires-Dist: pillow
Requires-Dist: mss
Requires-Dist: pygetwindow
Requires-Dist: gymnasium
Requires-Dist: vgamepad
